LICENSE
README.md
pyproject.toml
setup.py
phoneverify_cameroon/__init__.py
phoneverify_cameroon/exceptions.py
phoneverify_cameroon/models.py
phoneverify_cameroon/validator.py
phoneverify_cameroon.egg-info/PKG-INFO
phoneverify_cameroon.egg-info/SOURCES.txt
phoneverify_cameroon.egg-info/dependency_links.txt
phoneverify_cameroon.egg-info/not-zip-safe
phoneverify_cameroon.egg-info/requires.txt
phoneverify_cameroon.egg-info/top_level.txt
phoneverify_cameroon/data/operators.json
phoneverify_cameroon/tests/__init__.py
phoneverify_cameroon/tests/test_exceptions.py
phoneverify_cameroon/tests/test_integration.py
phoneverify_cameroon/tests/test_models.py
phoneverify_cameroon/tests/test_performance.py
phoneverify_cameroon/tests/test_validator.py
venv/Lib/site-packages/_black_version.py
venv/Lib/site-packages/inflection.py
venv/Lib/site-packages/mccabe.py
venv/Lib/site-packages/mypy_extensions.py
venv/Lib/site-packages/py.py
venv/Lib/site-packages/pycodestyle.py
venv/Lib/site-packages/typing_extensions.py
venv/Lib/site-packages/_pytest/__init__.py
venv/Lib/site-packages/_pytest/_argcomplete.py
venv/Lib/site-packages/_pytest/_version.py
venv/Lib/site-packages/_pytest/cacheprovider.py
venv/Lib/site-packages/_pytest/capture.py
venv/Lib/site-packages/_pytest/compat.py
venv/Lib/site-packages/_pytest/debugging.py
venv/Lib/site-packages/_pytest/deprecated.py
venv/Lib/site-packages/_pytest/doctest.py
venv/Lib/site-packages/_pytest/faulthandler.py
venv/Lib/site-packages/_pytest/fixtures.py
venv/Lib/site-packages/_pytest/freeze_support.py
venv/Lib/site-packages/_pytest/helpconfig.py
venv/Lib/site-packages/_pytest/hookspec.py
venv/Lib/site-packages/_pytest/junitxml.py
venv/Lib/site-packages/_pytest/legacypath.py
venv/Lib/site-packages/_pytest/logging.py
venv/Lib/site-packages/_pytest/main.py
venv/Lib/site-packages/_pytest/monkeypatch.py
venv/Lib/site-packages/_pytest/nodes.py
venv/Lib/site-packages/_pytest/outcomes.py
venv/Lib/site-packages/_pytest/pastebin.py
venv/Lib/site-packages/_pytest/pathlib.py
venv/Lib/site-packages/_pytest/py.typed
venv/Lib/site-packages/_pytest/pytester.py
venv/Lib/site-packages/_pytest/pytester_assertions.py
venv/Lib/site-packages/_pytest/python.py
venv/Lib/site-packages/_pytest/python_api.py
