Metadata-Version: 2.4
Name: phoneverify-cameroon
Version: 1.0.1
Summary: Validation des numéros mobile money camerounais (MTN et Orange)
Home-page: https://github.com/djoko-christian/phoneverify-cameroon
Author: Djoko Christian
Author-email: Djoko Christian <djoko.dev.pro@gmail.com>
License: MIT
Project-URL: Documentation, https://github.com/djokodev/PhoneVerify_Cameroon#readme
Project-URL: Repository, https://github.com/djokodev/PhoneVerify_Cameroon
Keywords: cameroon,mobile money,phone validation,MTN,ORANGE,fintech
Classifier: Intended Audience :: Developers
Classifier: License :: OSI Approved :: MIT License
Classifier: Programming Language :: Python :: 3
Classifier: Programming Language :: Python :: 3.8
Classifier: Programming Language :: Python :: 3.9
Classifier: Programming Language :: Python :: 3.10
Classifier: Programming Language :: Python :: 3.11
Classifier: Programming Language :: Python :: 3.12
Requires-Python: >=3.8
License-File: LICENSE
Provides-Extra: dev
Requires-Dist: pytest>=6.0; extra == "dev"
Requires-Dist: pytest-cov>=2.0; extra == "dev"
Requires-Dist: black>=21.0; extra == "dev"
Requires-Dist: flake8>=3.8; extra == "dev"
Requires-Dist: build>=0.7.0; extra == "dev"
Requires-Dist: twine>=3.0.0; extra == "dev"
Provides-Extra: test
Requires-Dist: pytest>=6.0; extra == "test"
Requires-Dist: pytest-cov>=2.0; extra == "test"
Dynamic: author
Dynamic: home-page
Dynamic: license-file
Dynamic: requires-python
